{
  "type": "Feature",
  "properties": {
    "gn:admin1_code":"30.0",
    "gn:admin2_code":"74800.0",
    "gn:asciiname":"Bolongo",
    "gn:country_code":"VI",
    "gn:dem":17,
    "gn:elevation":"15.0",
    "gn:feature_class":"P",
    "gn:feature_code":"PPL",
    "gn:name":"Bolongo",
    "gn:population":0,
    "gn:timezone":"America/St_Thomas",
    "iso:country":"VI",
    "wof:name":"Bolongo",
    "wof:placetype":"locality"
},
  "geometry": {"coordinates":[-64.8982,18.31745],"type":"Point"}
}