{
  "type": "Feature",
  "properties": {
    "gn:admin1_code":"10.0",
    "gn:admin2_code":"73900.0",
    "gn:asciiname":"Peters Rest",
    "gn:country_code":"VI",
    "gn:dem":57,
    "gn:elevation":"56.0",
    "gn:feature_class":"P",
    "gn:feature_code":"PPL",
    "gn:name":"Peters Rest",
    "gn:population":0,
    "gn:timezone":"America/St_Thomas",
    "iso:country":"VI",
    "wof:name":"Peters Rest",
    "wof:placetype":"locality"
},
  "geometry": {"coordinates":[-64.74054,17.72551],"type":"Point"}
}