{
  "type": "Feature",
  "properties": {
    "gn:admin1_code":"10.0",
    "gn:admin2_code":"73900.0",
    "gn:asciiname":"Upper Bethlehem",
    "gn:country_code":"VI",
    "gn:dem":33,
    "gn:elevation":"24.0",
    "gn:feature_class":"P",
    "gn:feature_code":"PPL",
    "gn:name":"Upper Bethlehem",
    "gn:population":0,
    "gn:timezone":"America/St_Thomas",
    "iso:country":"VI",
    "wof:name":"Upper Bethlehem",
    "wof:placetype":"locality"
},
  "geometry": {"coordinates":[-64.79209,17.71552999999999],"type":"Point"}
}