{
  "type": "Feature",
  "properties": {
    "gn:admin1_code":"10.0",
    "gn:admin2_code":"62200.0",
    "gn:asciiname":"William",
    "gn:country_code":"VI",
    "gn:dem":4,
    "gn:elevation":"3.0",
    "gn:feature_class":"P",
    "gn:feature_code":"PPL",
    "gn:name":"William",
    "gn:population":0,
    "gn:timezone":"America/St_Thomas",
    "iso:country":"VI",
    "name:bel_x_preferred":[
        "\u0423\u0456\u043b\u044c\u044f\u043c"
    ],
    "name:bre_x_preferred":[
        "William"
    ],
    "name:dan_x_preferred":[
        "William"
    ],
    "name:deu_x_preferred":[
        "William"
    ],
    "name:fas_x_preferred":[
        "\u0648\u06cc\u0644\u06cc\u0627\u0645"
    ],
    "name:fin_x_preferred":[
        "William"
    ],
    "name:fra_x_preferred":[
        "William"
    ],
    "name:isl_x_preferred":[
        "William"
    ],
    "name:kor_x_preferred":[
        "\uc70c\ub9ac\uc5c4"
    ],
    "name:nno_x_preferred":[
        "William"
    ],
    "name:nor_x_preferred":[
        "William"
    ],
    "name:ron_x_preferred":[
        "William"
    ],
    "name:rus_x_preferred":[
        "\u0423\u0438\u043b\u044c\u044f\u043c"
    ],
    "name:spa_x_preferred":[
        "William"
    ],
    "name:swe_x_preferred":[
        "William"
    ],
    "name:ukr_x_preferred":[
        "\u0412\u0456\u043b\u044c\u044f\u043c"
    ],
    "wof:name":"William",
    "wof:placetype":"locality"
},
  "geometry": {"coordinates":[-64.88875999999999,17.73442],"type":"Point"}
}