{
  "type": "Feature",
  "properties": {
    "gn:admin1_code":"10.0",
    "gn:admin2_code":"62200.0",
    "gn:asciiname":"William",
    "gn:country_code":"VI",
    "gn:dem":4,
    "gn:elevation":"3.0",
    "gn:feature_class":"P",
    "gn:feature_code":"PPL",
    "gn:name":"William",
    "gn:population":0,
    "gn:timezone":"America/St_Thomas",
    "iso:country":"VI",
    "wof:name":"William",
    "wof:placetype":"locality"
},
  "geometry": {"coordinates":[-64.88875999999999,17.73442],"type":"Point"}
}