{
  "type": "Feature",
  "properties": {
    "gn:admin1_code":"10.0",
    "gn:admin2_code":"4600.0",
    "gn:asciiname":"Fareham",
    "gn:country_code":"VI",
    "gn:dem":21,
    "gn:elevation":"18.0",
    "gn:feature_class":"P",
    "gn:feature_code":"PPL",
    "gn:name":"Fareham",
    "gn:population":0,
    "gn:timezone":"America/St_Thomas",
    "iso:country":"VI",
    "name:azb_x_preferred":[
        "\u0641\u0627\u0631\u0647\u0627\u0645"
    ],
    "name:ceb_x_preferred":[
        "Fareham"
    ],
    "name:cym_x_preferred":[
        "Fareham"
    ],
    "name:deu_x_preferred":[
        "Fareham"
    ],
    "name:fas_x_preferred":[
        "\u0641\u0627\u0631\u0647\u0627\u0645"
    ],
    "name:fin_x_preferred":[
        "Fareham"
    ],
    "name:fra_x_preferred":[
        "Fareham"
    ],
    "name:gle_x_preferred":[
        "Fareham"
    ],
    "name:ita_x_preferred":[
        "Fareham"
    ],
    "name:kor_x_preferred":[
        "\ud398\uc5b4\ub7fc"
    ],
    "name:lat_x_preferred":[
        "Fareham"
    ],
    "name:nno_x_preferred":[
        "Fareham"
    ],
    "name:nor_x_preferred":[
        "Fareham"
    ],
    "name:pol_x_preferred":[
        "Fareham"
    ],
    "name:ron_x_preferred":[
        "Fareham"
    ],
    "name:spa_x_preferred":[
        "Fareham"
    ],
    "name:swe_x_preferred":[
        "Fareham"
    ],
    "name:szl_x_preferred":[
        "Fareham"
    ],
    "name:tha_x_preferred":[
        "\u0e41\u0e1f\u0e23\u0e4c\u0e2d\u0e31\u0e21"
    ],
    "name:und_x_variant":[
        "Faraham",
        "Fairham",
        "Farnham"
    ],
    "name:vol_x_preferred":[
        "Fareham"
    ],
    "name:zho_x_preferred":[
        "\u8cbb\u52d2\u59c6"
    ],
    "wof:name":"Fareham",
    "wof:placetype":"locality"
},
  "geometry": {"coordinates":[-64.67041999999999,17.71552999999999],"type":"Point"}
}