{
  "type": "Feature",
  "properties": {
    "gn:admin1_code":"10.0",
    "gn:admin2_code":"4600.0",
    "gn:asciiname":"Fareham",
    "gn:country_code":"VI",
    "gn:dem":21,
    "gn:elevation":"18.0",
    "gn:feature_class":"P",
    "gn:feature_code":"PPL",
    "gn:name":"Fareham",
    "gn:population":0,
    "gn:timezone":"America/St_Thomas",
    "iso:country":"VI",
    "name:und_x_variant":[
        "Faraham",
        "Fairham",
        "Farnham"
    ],
    "wof:name":"Fareham",
    "wof:placetype":"locality"
},
  "geometry": {"coordinates":[-64.67041999999999,17.71552999999999],"type":"Point"}
}