{
  "type": "Feature",
  "properties": {
    "gn:admin1_code":"10.0",
    "gn:admin2_code":"71200.0",
    "gn:asciiname":"Strawberry Hill",
    "gn:country_code":"VI",
    "gn:dem":54,
    "gn:elevation":"45.0",
    "gn:feature_class":"P",
    "gn:feature_code":"PPL",
    "gn:name":"Strawberry Hill",
    "gn:population":0,
    "gn:timezone":"America/St_Thomas",
    "iso:country":"VI",
    "name:und_x_variant":[
        "Strawberryhill"
    ],
    "wof:name":"Strawberry Hill",
    "wof:placetype":"locality"
},
  "geometry": {"coordinates":[-64.76098,17.7322],"type":"Point"}
}