{
  "type": "Feature",
  "properties": {
    "gn:admin1_code":"10.0",
    "gn:admin2_code":"62200.0",
    "gn:asciiname":"Oxford",
    "gn:country_code":"VI",
    "gn:dem":101,
    "gn:elevation":"91.0",
    "gn:feature_class":"P",
    "gn:feature_code":"PPL",
    "gn:name":"Oxford",
    "gn:population":0,
    "gn:timezone":"America/St_Thomas",
    "iso:country":"VI",
    "wof:name":"Oxford",
    "wof:placetype":"locality"
},
  "geometry": {"coordinates":[-64.86098,17.73914],"type":"Point"}
}