{
  "type": "Feature",
  "properties": {
    "gn:admin1_code":"10.0",
    "gn:admin2_code":"62200.0",
    "gn:asciiname":"Montpellier",
    "gn:country_code":"VI",
    "gn:dem":160,
    "gn:elevation":"148.0",
    "gn:feature_class":"P",
    "gn:feature_code":"PPL",
    "gn:name":"Montpellier",
    "gn:population":0,
    "gn:timezone":"America/St_Thomas",
    "iso:country":"VI",
    "wof:name":"Montpellier",
    "wof:placetype":"locality"
},
  "geometry": {"coordinates":[-64.84236999999999,17.73886],"type":"Point"}
}