{
  "type": "Feature",
  "properties": {
    "gn:admin1_code":"10.0",
    "gn:admin2_code":"71200.0",
    "gn:asciiname":"Limetree",
    "gn:country_code":"VI",
    "gn:dem":61,
    "gn:elevation":"60.0",
    "gn:feature_class":"P",
    "gn:feature_code":"PPL",
    "gn:name":"Limetree",
    "gn:population":0,
    "gn:timezone":"America/St_Thomas",
    "iso:country":"VI",
    "name:und_x_variant":[
        "Hartman",
        "Hartmann"
    ],
    "wof:name":"Limetree",
    "wof:placetype":"locality"
},
  "geometry": {"coordinates":[-64.76430999999999,17.73692],"type":"Point"}
}