{
  "type": "Feature",
  "properties": {
    "gn:admin1_code":"30.0",
    "gn:admin2_code":"61300.0",
    "gn:asciiname":"Caret Bay Estate",
    "gn:country_code":"VI",
    "gn:dem":240,
    "gn:elevation":"242.0",
    "gn:feature_class":"P",
    "gn:feature_code":"PPL",
    "gn:name":"Caret Bay Estate",
    "gn:population":0,
    "gn:timezone":"America/St_Thomas",
    "iso:country":"VI",
    "name:und_x_variant":[
        "Caretbay Estate",
        "Carrettbay",
        "Carretbay"
    ],
    "wof:name":"Caret Bay Estate",
    "wof:placetype":"locality"
},
  "geometry": {"coordinates":[-64.97598000000001,18.36384],"type":"Point"}
}