{
  "type": "Feature",
  "properties": {
    "gn:admin1_code":"30.0",
    "gn:admin2_code":"61300.0",
    "gn:asciiname":"Solberg",
    "gn:country_code":"VI",
    "gn:dem":185,
    "gn:elevation":"186.0",
    "gn:feature_class":"P",
    "gn:feature_code":"PPL",
    "gn:name":"Solberg",
    "gn:population":0,
    "gn:timezone":"America/St_Thomas",
    "iso:country":"VI",
    "wof:name":"Solberg",
    "wof:placetype":"locality"
},
  "geometry": {"coordinates":[-64.94181,18.34746],"type":"Point"}
}