{
  "type": "Feature",
  "properties": {
    "iso:country":"VI",
    "name:dut_x_preferred":[
        "Great Pond"
    ],
    "name:eng_x_preferred":[
        "Great Pond"
    ],
    "qs:gn_country":"VI",
    "qs:gn_fcode":"PPL",
    "qs:gn_pop":0,
    "qs:name":"Great Pond",
    "qs:name_adm0":"US Virgin Islands",
    "qs:name_adm1":"Saint Croix Island",
    "qs:photos":14,
    "qs:photos_1k":3,
    "qs:photos_9k":1,
    "qs:photos_9r":1,
    "qs:photos_all":14,
    "qs:photos_sr":1,
    "qs:placetype":"Town",
    "qs:pop_sr":"0",
    "qs:woe_adm0":23424985,
    "wd:wordcount":314,
    "wof:name":"Great Pond",
    "wof:placetype":"locality"
},
  "geometry": {"coordinates":[-64.64875000000001,17.72442],"type":"Point"}
}