{
  "type": "Feature",
  "properties": {
    "gn:admin1_code":"30.0",
    "gn:admin2_code":"61300.0",
    "gn:asciiname":"Neltjeberg",
    "gn:country_code":"VI",
    "gn:dem":207,
    "gn:elevation":"215.0",
    "gn:feature_class":"P",
    "gn:feature_code":"PPL",
    "gn:name":"Neltjeberg",
    "gn:population":0,
    "gn:timezone":"America/St_Thomas",
    "iso:country":"VI",
    "wof:name":"Neltjeberg",
    "wof:placetype":"locality"
},
  "geometry": {"coordinates":[-64.97292,18.36607],"type":"Point"}
}