{
  "type": "Feature",
  "properties": {
    "iso:country":"VI",
    "name:und_x_variant":[
        "Let-Alone"
    ],
    "qs:gn_country":"VI",
    "qs:gn_fcode":"PPL",
    "qs:gn_pop":0,
    "qs:name":"Lerkenlund",
    "qs:name_adm0":"US Virgin Islands",
    "qs:name_adm1":"Saint Thomas Island",
    "qs:photos":18,
    "qs:photos_1k":4,
    "qs:photos_9k":1,
    "qs:photos_9r":1,
    "qs:photos_all":18,
    "qs:photos_sr":1,
    "qs:placetype":"Town",
    "qs:pop_sr":"0",
    "qs:woe_adm0":23424985,
    "wof:name":"Lerkenlund",
    "wof:placetype":"locality"
},
  "geometry": {"coordinates":[-64.94015,18.36023],"type":"Point"}
}