{
  "type": "Feature",
  "properties": {
    "gn:admin1_code":"10.0",
    "gn:admin2_code":"59500.0",
    "gn:asciiname":"Canaan",
    "gn:country_code":"VI",
    "gn:dem":129,
    "gn:elevation":"134.0",
    "gn:feature_class":"P",
    "gn:feature_code":"PPL",
    "gn:name":"Canaan",
    "gn:population":0,
    "gn:timezone":"America/St_Thomas",
    "iso:country":"VI",
    "wof:name":"Canaan",
    "wof:placetype":"locality"
},
  "geometry": {"coordinates":[-64.79653,17.76025],"type":"Point"}
}