{
  "type": "Feature",
  "properties": {
    "gn:admin1_code":"20.0",
    "gn:admin2_code":"15400.0",
    "gn:asciiname":"Palestina",
    "gn:country_code":"VI",
    "gn:dem":26,
    "gn:elevation":"15.0",
    "gn:feature_class":"P",
    "gn:feature_code":"PPL",
    "gn:name":"Palestina",
    "gn:population":0,
    "gn:timezone":"America/St_Thomas",
    "iso:country":"VI",
    "name:und_x_variant":[
        "Palestine"
    ],
    "wof:name":"Palestina",
    "wof:placetype":"locality"
},
  "geometry": {"coordinates":[-64.7068,18.34884],"type":"Point"}
}