{
  "type": "Feature",
  "properties": {
    "gn:admin1_code":"10.0",
    "gn:admin2_code":"38800.0",
    "gn:asciiname":"Smithfield",
    "gn:country_code":"VI",
    "gn:dem":30,
    "gn:elevation":"26.0",
    "gn:feature_class":"P",
    "gn:feature_code":"PPL",
    "gn:name":"Smithfield",
    "gn:population":0,
    "gn:timezone":"America/St_Thomas",
    "iso:country":"VI",
    "name:cat_x_preferred":[
        "Smithfield"
    ],
    "name:ceb_x_preferred":[
        "Smithfield"
    ],
    "name:ces_x_preferred":[
        "Smithfield"
    ],
    "name:deu_x_preferred":[
        "Smithfield"
    ],
    "name:est_x_preferred":[
        "Smithfield"
    ],
    "name:fin_x_preferred":[
        "Smithfield"
    ],
    "name:fra_x_preferred":[
        "Smithfield"
    ],
    "name:ind_x_preferred":[
        "Smithfield"
    ],
    "name:ita_x_preferred":[
        "Smithfield"
    ],
    "name:nds_x_preferred":[
        "Smithfield"
    ],
    "name:nld_x_preferred":[
        "Smithfield"
    ],
    "name:nor_x_preferred":[
        "Smithfield"
    ],
    "name:pol_x_preferred":[
        "Smithfield"
    ],
    "name:por_x_preferred":[
        "Smithfield"
    ],
    "name:ron_x_preferred":[
        "Smithfield"
    ],
    "name:rus_x_preferred":[
        "\u0421\u043c\u0438\u0442\u0444\u0438\u043b\u0434"
    ],
    "name:spa_x_preferred":[
        "Smithfield"
    ],
    "name:srp_x_preferred":[
        "\u0421\u043c\u0438\u0442\u0444\u0438\u043b\u0434"
    ],
    "name:swe_x_preferred":[
        "Smithfield"
    ],
    "name:und_x_variant":[
        "Smithfjeld",
        "Smith's Field"
    ],
    "name:urd_x_preferred":[
        "\u0633\u0645\u062a\u06be\u0641\u06cc\u0644\u0688"
    ],
    "name:vol_x_preferred":[
        "Smithfield"
    ],
    "wof:name":"Smithfield",
    "wof:placetype":"locality"
},
  "geometry": {"coordinates":[-64.88042,17.6997],"type":"Point"}
}