{
  "type": "Feature",
  "properties": {
    "gn:admin1_code":"10.0",
    "gn:admin2_code":"62200.0",
    "gn:asciiname":"Waldberggaard",
    "gn:country_code":"VI",
    "gn:dem":78,
    "gn:elevation":"68.0",
    "gn:feature_class":"P",
    "gn:feature_code":"PPL",
    "gn:name":"Waldberggaard",
    "gn:population":0,
    "gn:timezone":"America/St_Thomas",
    "iso:country":"VI",
    "name:und_x_variant":[
        "Walberggaard",
        "Waldberg Gaard",
        "Watberg Gaard",
        "Walberg Guard"
    ],
    "wof:name":"Waldberggaard",
    "wof:placetype":"locality"
},
  "geometry": {"coordinates":[-64.84430999999999,17.71663999999999],"type":"Point"}
}