{
  "type": "Feature",
  "properties": {
    "gn:admin1_code":"10.0",
    "gn:admin2_code":"62200.0",
    "gn:asciiname":"Hard Labour",
    "gn:country_code":"VI",
    "gn:dem":180,
    "gn:elevation":"174.0",
    "gn:feature_class":"P",
    "gn:feature_code":"PPL",
    "gn:name":"Hard Labour",
    "gn:population":0,
    "gn:timezone":"America/St_Thomas",
    "iso:country":"VI",
    "name:und_x_variant":[
        "Hardlabor",
        "Hard Labor"
    ],
    "wof:name":"Hard Labour",
    "wof:placetype":"locality"
},
  "geometry": {"coordinates":[-64.82653000000001,17.74108],"type":"Point"}
}