{
  "type": "Feature",
  "properties": {
    "iso:country":"VI",
    "qs:gn_country":"VI",
    "qs:gn_fcode":"PPL",
    "qs:gn_pop":0,
    "qs:name":"Mary Point",
    "qs:name_adm0":"US Virgin Islands",
    "qs:name_adm1":"Saint John Island",
    "qs:photos":493,
    "qs:photos_1k":100,
    "qs:photos_9k":2,
    "qs:photos_9r":5,
    "qs:photos_all":493,
    "qs:photos_sr":7,
    "qs:placetype":"Town",
    "qs:pop_sr":"0",
    "qs:woe_adm0":23424985,
    "wof:name":"Mary Point",
    "wof:placetype":"locality"
},
  "geometry": {"coordinates":[-64.7418,18.36523],"type":"Point"}
}